app/__init__.py
app/main.py
app/api/__init__.py
app/api/routes/__init__.py
app/api/routes/health.py
app/api/routes/meta.py
app/core/__init__.py
app/core/config.py
app/core/decorators.py
app/core/lifespan.py
app/core/logging.py
app/core/middleware.py
app/dependencies/__init__.py
app/dependencies/config.py
app/dependencies/services.py
app/integrations/alerting.py
app/middleware/__init__.py
app/middleware/advanced.py
app/middleware/auth.py
app/middleware/monitoring.py
app/middleware/rate_limit.py
app/middleware/security.py
app/schemas/__init__.py
app/schemas/health.py
app/services/__init__.py
app/services/health.py
app/utils/__init__.py
fastapi_production_starter-1.0.1.dist-info/METADATA
fastapi_production_starter-1.0.1.dist-info/WHEEL
fastapi_production_starter-1.0.1.dist-info/licenses/LICENSE
fastapi_production_starter-1.0.1.dist-info/RECORD
