Metadata-Version: 2.4
Name: fastapi-production-starter
Version: 1.0.1
Summary: Production-ready FastAPI starter template with security, observability, and modern Python best practices built-in.
Project-URL: homepage, https://github.com/thesidshah/FastAPI-Backend-Template
Project-URL: repository, https://github.com/thesidshah/FastAPI-Backend-Template
Project-URL: documentation, https://github.com/thesidshah/FastAPI-Backend-Template#readme
Project-URL: issues, https://github.com/thesidshah/FastAPI-Backend-Template/issues
Author: Siddhant Shah
License: MIT
License-File: LICENSE
Keywords: api,async,fastapi,production,security,starter,template
Classifier: Development Status :: 4 - Beta
Classifier: Framework :: FastAPI
Classifier: Intended Audience :: Developers
Classifier: License :: OSI Approved :: MIT License
Classifier: Programming Language :: Python :: 3
Classifier: Programming Language :: Python :: 3.11
Classifier: Programming Language :: Python :: 3.12
Classifier: Topic :: Internet :: WWW/HTTP :: HTTP Servers
Classifier: Topic :: Software Development :: Libraries :: Application Frameworks
Requires-Python: >=3.11
Requires-Dist: fastapi<0.112,>=0.111
Requires-Dist: orjson<4.0,>=3.10
Requires-Dist: pydantic-settings<3.0,>=2.3
Requires-Dist: python-dotenv<2.0,>=1.0
Requires-Dist: structlog<25.0,>=24.2
Requires-Dist: uvicorn[standard]<0.31,>=0.30
Provides-Extra: dev
Requires-Dist: black<25.0,>=24.4; extra == 'dev'
Requires-Dist: httpx<0.28,>=0.27; extra == 'dev'
Requires-Dist: mypy<2.0,>=1.10; extra == 'dev'
Requires-Dist: pytest-asyncio<0.24,>=0.23; extra == 'dev'
Requires-Dist: pytest-cov<6.0,>=5.0; extra == 'dev'
Requires-Dist: pytest<9.0,>=8.2; extra == 'dev'
Requires-Dist: ruff<0.5,>=0.4; extra == 'dev'
Provides-Extra: phase2
Requires-Dist: cryptography<42.0,>=41.0; extra == 'phase2'
Requires-Dist: hiredis<3.0,>=2.2; extra == 'phase2'
Requires-Dist: pyjwt<3.0,>=2.8; extra == 'phase2'
Requires-Dist: redis<6.0,>=5.0; extra == 'phase2'
Provides-Extra: phase3
Requires-Dist: geoip2<5.0,>=4.7; extra == 'phase3'
Requires-Dist: prometheus-client<0.20,>=0.19; extra == 'phase3'
Provides-Extra: security
Requires-Dist: cryptography<42.0,>=41.0; extra == 'security'
Requires-Dist: geoip2<5.0,>=4.7; extra == 'security'
Requires-Dist: hiredis<3.0,>=2.2; extra == 'security'
Requires-Dist: prometheus-client<0.20,>=0.19; extra == 'security'
Requires-Dist: pyjwt<3.0,>=2.8; extra == 'security'
Requires-Dist: redis<6.0,>=5.0; extra == 'security'
